{
  "$schema": "https://ui.shadcn.com/schema/registry-item.json",
  "name": "dock-menu",
  "type": "registry:ui",
  "title": "Dock Menu",
  "description": "A macOS-style dock with smooth magnification effect powered by Framer Motion spring physics and motion values.",
  "dependencies": [
    "framer-motion"
  ],
  "registryDependencies": [],
  "files": [
    {
      "path": "components/flexui/dock-menu.tsx",
      "content": "\"use client\";\n\nimport React, { useRef, Children, cloneElement, isValidElement } from \"react\";\nimport {\n  motion,\n  useMotionValue,\n  useSpring,\n  useTransform,\n  type MotionValue,\n  AnimatePresence,\n} from \"framer-motion\";\nimport { cn } from \"@/lib/utils\";\n\n/* ─── Types ──────────────────────────────────────────────────────────────── */\n\ninterface DockItem {\n  icon: React.ReactNode;\n  label: string;\n  onClick?: () => void;\n}\n\ninterface DockMenuProps {\n  items: DockItem[];\n  className?: string;\n  /** Base icon size in px @default 48 */\n  iconSize?: number;\n  /** Max magnified size in px @default 72 */\n  magnification?: number;\n  /** Distance of magnification effect in px @default 150 */\n  distance?: number;\n}\n\n/* ─── Single Dock Icon ───────────────────────────────────────────────────── */\n\nfunction DockIcon({\n  item,\n  mouseX,\n  iconSize,\n  magnification,\n  distance,\n}: {\n  item: DockItem;\n  mouseX: MotionValue<number>;\n  iconSize: number;\n  magnification: number;\n  distance: number;\n}) {\n  const ref = useRef<HTMLButtonElement>(null);\n  const [hovered, setHovered] = React.useState(false);\n\n  // Distance from mouse to icon center\n  const distanceFromMouse = useTransform(mouseX, (val: number) => {\n    const el = ref.current;\n    if (!el) return distance + 1;\n    const rect = el.getBoundingClientRect();\n    return val - rect.left - rect.width / 2;\n  });\n\n  // Map distance → size: 0 distance = magnification, far = iconSize\n  const sizeTransform = useTransform(\n    distanceFromMouse,\n    [-distance, 0, distance],\n    [iconSize, magnification, iconSize]\n  );\n\n  const size = useSpring(sizeTransform, {\n    mass: 0.1,\n    stiffness: 150,\n    damping: 12,\n  });\n\n  return (\n    <div className=\"relative flex flex-col items-center\">\n      {/* Tooltip */}\n      <AnimatePresence>\n        {hovered && (\n          <motion.div\n            initial={{ opacity: 0, y: 4, scale: 0.9 }}\n            animate={{ opacity: 1, y: 0, scale: 1 }}\n            exit={{ opacity: 0, y: 4, scale: 0.9 }}\n            transition={{ duration: 0.15 }}\n            className=\"absolute -top-10 whitespace-nowrap rounded-lg border border-white/[0.08] bg-zinc-900/90 px-3 py-1.5 text-xs font-medium text-white shadow-xl backdrop-blur-sm\"\n          >\n            {item.label}\n          </motion.div>\n        )}\n      </AnimatePresence>\n\n      <motion.button\n        ref={ref}\n        onMouseEnter={() => setHovered(true)}\n        onMouseLeave={() => setHovered(false)}\n        onClick={item.onClick}\n        whileTap={{ scale: 0.85 }}\n        style={{ width: size, height: size }}\n        className=\"flex items-center justify-center rounded-xl bg-white/[0.06] text-zinc-300 transition-colors hover:bg-white/[0.1]\"\n      >\n        <div className=\"flex h-1/2 w-1/2 items-center justify-center\">\n          {item.icon}\n        </div>\n      </motion.button>\n    </div>\n  );\n}\n\n/* ─── Dock Menu ──────────────────────────────────────────────────────────── */\n\nexport function DockMenu({\n  items,\n  className,\n  iconSize = 48,\n  magnification = 72,\n  distance = 150,\n}: DockMenuProps) {\n  const mouseX = useMotionValue(Infinity);\n\n  return (\n    <motion.div\n      onMouseMove={(e) => mouseX.set(e.pageX)}\n      onMouseLeave={() => mouseX.set(Infinity)}\n      className={cn(\n        \"inline-flex items-end gap-2 rounded-2xl border border-white/[0.08] bg-zinc-950/80 px-4 py-3 backdrop-blur-xl\",\n        className\n      )}\n    >\n      {items.map((item, i) => (\n        <DockIcon\n          key={item.label + i}\n          item={item}\n          mouseX={mouseX}\n          iconSize={iconSize}\n          magnification={magnification}\n          distance={distance}\n        />\n      ))}\n    </motion.div>\n  );\n}\n",
      "type": "registry:ui",
      "target": "components/flexui/dock-menu.tsx"
    }
  ]
}